{
	"credit": "Made with Blockbench",
	"parent": "minecraft:block/block",
	"textures": {
		"particle": "affinity:block/emerald_block",
		"all": "affinity:block/emerald_block"
	},
	"elements": [
		{
			"from": [0, 15, 0],
			"to": [16, 16, 16],
			"faces": {
				"north": {"uv": [0, 0, 16, 1], "texture": "#all", "cullface": "north"},
				"east": {"uv": [0, 0, 16, 1], "texture": "#all", "cullface": "east"},
				"south": {"uv": [0, 0, 16, 1], "texture": "#all", "cullface": "south"},
				"west": {"uv": [0, 0, 16, 1], "texture": "#all", "cullface": "west"},
				"up": {"uv": [0, 0, 16, 16], "texture": "#all", "cullface": "up"},
				"down": {"uv": [0, 0, 16, 16], "texture": "#all"}
			}
		},
		{
			"from": [0, 0, 0],
			"to": [16, 1, 16],
			"faces": {
				"north": {"uv": [0, 15, 16, 16], "texture": "#all", "cullface": "north"},
				"east": {"uv": [0, 15, 16, 16], "texture": "#all", "cullface": "east"},
				"south": {"uv": [0, 15, 16, 16], "texture": "#all", "cullface": "south"},
				"west": {"uv": [0, 15, 16, 16], "texture": "#all", "cullface": "west"},
				"up": {"uv": [0, 0, 16, 16], "texture": "#all"},
				"down": {"uv": [0, 0, 16, 16], "texture": "#all", "cullface": "down"}
			}
		},
		{
			"from": [0, 1, 0],
			"to": [1, 15, 16],
			"faces": {
				"north": {"uv": [15, 1, 16, 15], "texture": "#all", "cullface": "north"},
				"east": {"uv": [0, 1, 16, 15], "texture": "#all"},
				"south": {"uv": [0, 1, 1, 15], "texture": "#all", "cullface": "south"},
				"west": {"uv": [0, 1, 16, 15], "texture": "#all", "cullface": "west"},
				"up": {"uv": [0, 0, 0, 0], "texture": "#all"},
				"down": {"uv": [0, 0, 0, 0], "texture": "#all"}
			}
		},
		{
			"from": [15, 1, 0],
			"to": [16, 15, 16],
			"faces": {
				"north": {"uv": [0, 1, 1, 15], "texture": "#all", "cullface": "north"},
				"east": {"uv": [0, 1, 16, 15], "texture": "#all", "cullface": "east"},
				"south": {"uv": [15, 1, 16, 15], "texture": "#all", "cullface": "south"},
				"west": {"uv": [0, 1, 16, 15], "texture": "#all"},
				"up": {"uv": [0, 0, 0, 0], "texture": "#all"},
				"down": {"uv": [0, 0, 0, 0], "texture": "#all"}
			}
		},
		{
			"from": [1, 1, 0],
			"to": [15, 15, 1],
			"faces": {
				"north": {"uv": [1, 1, 15, 15], "texture": "#all", "cullface": "north"},
				"east": {"uv": [0, 0, 0, 0], "texture": "#all"},
				"south": {"uv": [1, 1, 15, 15], "texture": "#all"},
				"west": {"uv": [0, 0, 0, 0], "texture": "#all"},
				"up": {"uv": [0, 0, 0, 0], "texture": "#all"},
				"down": {"uv": [0, 0, 0, 0], "texture": "#all"}
			}
		},
		{
			"from": [1, 1, 15],
			"to": [15, 15, 16],
			"faces": {
				"north": {"uv": [1, 1, 15, 15], "texture": "#all"},
				"east": {"uv": [0, 0, 0, 0], "texture": "#all"},
				"south": {"uv": [1, 1, 15, 15], "texture": "#all", "cullface": "south"},
				"west": {"uv": [0, 0, 0, 0], "texture": "#all"},
				"up": {"uv": [0, 0, 0, 0], "texture": "#all"},
				"down": {"uv": [0, 0, 0, 0], "texture": "#all"}
			}
		}
	]
}