{
  "parent": "affinity:isnt_it_iron_sword",
  "display": {
    "icon": {
      "id": "affinity:stabilized_artifact_blade"
    },
    "title": {
      "translate": "advancement.affinity.unbreakable.title"
    },
    "description": {
      "translate": "advancement.affinity.unbreakable.description"
    },
    "frame": "task",
    "show_toast": true,
    "announce_to_chat": true,
    "hidden": false
  },
  "criteria": {
    "stabilized_artifact_blade": {
      "trigger": "minecraft:inventory_changed",
      "conditions": {
        "items": [
          {
            "items":[
              "affinity:stabilized_artifact_blade"
            ]
          }
        ]
      }
    }
  },
  "requirements": [
    [
      "stabilized_artifact_blade"
    ]
  ]
}